{
    "tags": [],
    "description": "",
    "objects": [
        {
            "id": 1173272103,
            "classId": 11386592,
            "description": "",
            "geometryType": "rectangle",
            "labelerLogin": "masum",
            "createdAt": "2023-01-28T14:51:55.102Z",
            "updatedAt": "2023-01-28T14:52:01.487Z",
            "tags": [],
            "classTitle": "shrimp",
            "points": {
                "exterior": [
                    [
                        197.0,
                        0.0
                    ],
                    [
                        299.0,
                        130.0
                    ]
                ],
                "interior": []
            }
        },
        {
            "id": 1173272107,
            "classId": 11386592,
            "description": "",
            "geometryType": "rectangle",
            "labelerLogin": "masum",
            "createdAt": "2023-01-28T14:51:59.231Z",
            "updatedAt": "2023-01-28T14:52:04.212Z",
            "tags": [],
            "classTitle": "shrimp",
            "points": {
                "exterior": [
                    [
                        272.0,
                        0.0
                    ],
                    [
                        284.0,
                        23.0
                    ]
                ],
                "interior": []
            }
        },
        {
            "id": 1173272109,
            "classId": 11386592,
            "description": "",
            "geometryType": "rectangle",
            "labelerLogin": "masum",
            "createdAt": "2023-01-28T14:52:03.552Z",
            "updatedAt": "2023-01-28T14:52:03.552Z",
            "tags": [],
            "classTitle": "shrimp",
            "points": {
                "exterior": [
                    [
                        246.0,
                        216.0
                    ],
                    [
                        299.0,
                        239.0
                    ]
                ],
                "interior": []
            }
        }
    ],
    "size": {
        "height": 240,
        "width": 320
    }
}