{
    "tags": [],
    "description": "",
    "objects": [
        {
            "id": 1173221480,
            "classId": 11386592,
            "description": "",
            "geometryType": "rectangle",
            "labelerLogin": "Rakib123",
            "createdAt": "2023-01-28T12:21:52.722Z",
            "updatedAt": "2023-01-28T12:21:59.783Z",
            "tags": [],
            "classTitle": "shrimp",
            "points": {
                "exterior": [
                    [
                        176.0,
                        0.0
                    ],
                    [
                        271.0,
                        169.0
                    ]
                ],
                "interior": []
            }
        },
        {
            "id": 1173221482,
            "classId": 11386592,
            "description": "",
            "geometryType": "rectangle",
            "labelerLogin": "Rakib123",
            "createdAt": "2023-01-28T12:21:56.041Z",
            "updatedAt": "2023-01-28T12:21:59.783Z",
            "tags": [],
            "classTitle": "shrimp",
            "points": {
                "exterior": [
                    [
                        218.0,
                        143.0
                    ],
                    [
                        270.0,
                        239.0
                    ]
                ],
                "interior": []
            }
        },
        {
            "id": 1173221483,
            "classId": 11386592,
            "description": "",
            "geometryType": "rectangle",
            "labelerLogin": "Rakib123",
            "createdAt": "2023-01-28T12:21:59.393Z",
            "updatedAt": "2023-01-28T12:21:59.393Z",
            "tags": [],
            "classTitle": "shrimp",
            "points": {
                "exterior": [
                    [
                        198.0,
                        190.0
                    ],
                    [
                        248.0,
                        239.0
                    ]
                ],
                "interior": []
            }
        }
    ],
    "size": {
        "height": 240,
        "width": 320
    }
}