{
    "tags": [],
    "description": "",
    "objects": [
        {
            "id": 1173258031,
            "classId": 11386592,
            "description": "",
            "geometryType": "rectangle",
            "labelerLogin": "abunoman",
            "createdAt": "2023-01-28T13:13:00.509Z",
            "updatedAt": "2023-01-28T13:13:00.509Z",
            "tags": [],
            "classTitle": "shrimp",
            "points": {
                "exterior": [
                    [
                        5.0,
                        126.0
                    ],
                    [
                        92.0,
                        239.0
                    ]
                ],
                "interior": []
            }
        }
    ],
    "size": {
        "height": 240,
        "width": 320
    }
}