{
    "tags": [],
    "description": "",
    "objects": [
        {
            "id": 1173181039,
            "classId": 11386592,
            "description": "",
            "geometryType": "rectangle",
            "labelerLogin": "Rakib123",
            "createdAt": "2023-01-28T04:51:01.818Z",
            "updatedAt": "2023-01-28T04:51:12.781Z",
            "tags": [],
            "classTitle": "shrimp",
            "points": {
                "exterior": [
                    [
                        56.0,
                        90.0
                    ],
                    [
                        114.0,
                        174.0
                    ]
                ],
                "interior": []
            }
        },
        {
            "id": 1173181040,
            "classId": 11386592,
            "description": "",
            "geometryType": "rectangle",
            "labelerLogin": "Rakib123",
            "createdAt": "2023-01-28T04:51:04.738Z",
            "updatedAt": "2023-01-28T04:51:12.781Z",
            "tags": [],
            "classTitle": "shrimp",
            "points": {
                "exterior": [
                    [
                        61.0,
                        143.0
                    ],
                    [
                        109.0,
                        239.0
                    ]
                ],
                "interior": []
            }
        },
        {
            "id": 1173181043,
            "classId": 11386592,
            "description": "",
            "geometryType": "rectangle",
            "labelerLogin": "Rakib123",
            "createdAt": "2023-01-28T04:51:07.476Z",
            "updatedAt": "2023-01-28T04:51:12.781Z",
            "tags": [],
            "classTitle": "shrimp",
            "points": {
                "exterior": [
                    [
                        137.0,
                        177.0
                    ],
                    [
                        175.0,
                        239.0
                    ]
                ],
                "interior": []
            }
        },
        {
            "id": 1173181046,
            "classId": 11386592,
            "description": "",
            "geometryType": "rectangle",
            "labelerLogin": "Rakib123",
            "createdAt": "2023-01-28T04:51:12.324Z",
            "updatedAt": "2023-01-28T04:51:12.324Z",
            "tags": [],
            "classTitle": "shrimp",
            "points": {
                "exterior": [
                    [
                        216.0,
                        42.0
                    ],
                    [
                        280.0,
                        239.0
                    ]
                ],
                "interior": []
            }
        }
    ],
    "size": {
        "height": 240,
        "width": 320
    }
}