{
    "tags": [],
    "description": "",
    "objects": [
        {
            "id": 1173266525,
            "classId": 11386592,
            "description": "",
            "geometryType": "rectangle",
            "labelerLogin": "masum",
            "createdAt": "2023-01-28T14:23:53.830Z",
            "updatedAt": "2023-01-28T14:24:02.432Z",
            "tags": [],
            "classTitle": "shrimp",
            "points": {
                "exterior": [
                    [
                        62.0,
                        123.0
                    ],
                    [
                        112.0,
                        239.0
                    ]
                ],
                "interior": []
            }
        },
        {
            "id": 1173266527,
            "classId": 11386592,
            "description": "",
            "geometryType": "rectangle",
            "labelerLogin": "masum",
            "createdAt": "2023-01-28T14:23:58.215Z",
            "updatedAt": "2023-01-28T14:24:02.432Z",
            "tags": [],
            "classTitle": "shrimp",
            "points": {
                "exterior": [
                    [
                        241.0,
                        32.0
                    ],
                    [
                        289.0,
                        169.0
                    ]
                ],
                "interior": []
            }
        },
        {
            "id": 1173266528,
            "classId": 11386592,
            "description": "",
            "geometryType": "rectangle",
            "labelerLogin": "masum",
            "createdAt": "2023-01-28T14:24:01.346Z",
            "updatedAt": "2023-01-28T14:24:01.346Z",
            "tags": [],
            "classTitle": "shrimp",
            "points": {
                "exterior": [
                    [
                        259.0,
                        231.0
                    ],
                    [
                        295.0,
                        239.0
                    ]
                ],
                "interior": []
            }
        }
    ],
    "size": {
        "height": 240,
        "width": 320
    }
}