{
    "tags": [],
    "description": "",
    "objects": [
        {
            "id": 1173234966,
            "classId": 11386592,
            "description": "",
            "geometryType": "rectangle",
            "labelerLogin": "abunoman",
            "createdAt": "2023-01-28T12:36:53.954Z",
            "updatedAt": "2023-01-28T12:36:53.954Z",
            "tags": [],
            "classTitle": "shrimp",
            "points": {
                "exterior": [
                    [
                        249.0,
                        4.0
                    ],
                    [
                        294.0,
                        237.0
                    ]
                ],
                "interior": []
            }
        }
    ],
    "size": {
        "height": 240,
        "width": 320
    }
}