{
    "tags": [],
    "description": "",
    "objects": [
        {
            "id": 1173182677,
            "classId": 11386592,
            "description": "",
            "geometryType": "rectangle",
            "labelerLogin": "abunoman",
            "createdAt": "2023-01-28T05:25:56.496Z",
            "updatedAt": "2023-01-28T05:26:00.091Z",
            "tags": [],
            "classTitle": "shrimp",
            "points": {
                "exterior": [
                    [
                        238.0,
                        0.0
                    ],
                    [
                        266.0,
                        70.0
                    ]
                ],
                "interior": []
            }
        }
    ],
    "size": {
        "height": 240,
        "width": 320
    }
}