{
    "tags": [],
    "description": "",
    "objects": [
        {
            "id": 1173186518,
            "classId": 11386592,
            "description": "",
            "geometryType": "rectangle",
            "labelerLogin": "abunoman",
            "createdAt": "2023-01-28T06:53:58.429Z",
            "updatedAt": "2023-01-28T06:54:02.490Z",
            "tags": [],
            "classTitle": "shrimp",
            "points": {
                "exterior": [
                    [
                        145.0,
                        151.0
                    ],
                    [
                        181.0,
                        239.0
                    ]
                ],
                "interior": []
            }
        }
    ],
    "size": {
        "height": 240,
        "width": 320
    }
}