{
    "tags": [],
    "description": "",
    "objects": [
        {
            "id": 1173195158,
            "classId": 11386592,
            "description": "",
            "geometryType": "rectangle",
            "labelerLogin": "Rakib123",
            "createdAt": "2023-01-28T11:24:38.344Z",
            "updatedAt": "2023-01-28T11:24:41.559Z",
            "tags": [],
            "classTitle": "shrimp",
            "points": {
                "exterior": [
                    [
                        244.0,
                        0.0
                    ],
                    [
                        278.0,
                        115.0
                    ]
                ],
                "interior": []
            }
        },
        {
            "id": 1173195161,
            "classId": 11386592,
            "description": "",
            "geometryType": "rectangle",
            "labelerLogin": "Rakib123",
            "createdAt": "2023-01-28T11:24:41.312Z",
            "updatedAt": "2023-01-28T11:24:41.312Z",
            "tags": [],
            "classTitle": "shrimp",
            "points": {
                "exterior": [
                    [
                        205.0,
                        213.0
                    ],
                    [
                        279.0,
                        239.0
                    ]
                ],
                "interior": []
            }
        }
    ],
    "size": {
        "height": 240,
        "width": 320
    }
}