{
    "tags": [],
    "description": "",
    "objects": [
        {
            "id": 1173233491,
            "classId": 11386592,
            "description": "",
            "geometryType": "rectangle",
            "labelerLogin": "abunoman",
            "createdAt": "2023-01-28T12:36:26.922Z",
            "updatedAt": "2023-01-28T12:36:26.922Z",
            "tags": [],
            "classTitle": "shrimp",
            "points": {
                "exterior": [
                    [
                        241.0,
                        0.0
                    ],
                    [
                        293.0,
                        155.0
                    ]
                ],
                "interior": []
            }
        }
    ],
    "size": {
        "height": 240,
        "width": 320
    }
}