{
    "tags": [],
    "description": "",
    "objects": [
        {
            "id": 1173190246,
            "classId": 11386592,
            "description": "",
            "geometryType": "rectangle",
            "labelerLogin": "abunoman",
            "createdAt": "2023-01-28T08:35:36.984Z",
            "updatedAt": "2023-01-28T08:35:36.984Z",
            "tags": [],
            "classTitle": "shrimp",
            "points": {
                "exterior": [
                    [
                        249.0,
                        134.0
                    ],
                    [
                        296.0,
                        240.0
                    ]
                ],
                "interior": []
            }
        }
    ],
    "size": {
        "height": 240,
        "width": 320
    }
}