{
    "tags": [],
    "description": "",
    "objects": [
        {
            "id": 1173187690,
            "classId": 11386592,
            "description": "",
            "geometryType": "rectangle",
            "labelerLogin": "masum",
            "createdAt": "2023-01-28T07:26:01.100Z",
            "updatedAt": "2023-01-28T07:26:06.209Z",
            "tags": [],
            "classTitle": "shrimp",
            "points": {
                "exterior": [
                    [
                        210.0,
                        133.0
                    ],
                    [
                        258.0,
                        239.0
                    ]
                ],
                "interior": []
            }
        },
        {
            "id": 1173187693,
            "classId": 11386592,
            "description": "",
            "geometryType": "rectangle",
            "labelerLogin": "masum",
            "createdAt": "2023-01-28T07:26:05.905Z",
            "updatedAt": "2023-01-28T07:26:05.905Z",
            "tags": [],
            "classTitle": "shrimp",
            "points": {
                "exterior": [
                    [
                        174.0,
                        123.0
                    ],
                    [
                        224.0,
                        239.0
                    ]
                ],
                "interior": []
            }
        }
    ],
    "size": {
        "height": 240,
        "width": 320
    }
}