{
    "tags": [],
    "description": "",
    "objects": [
        {
            "id": 1173192848,
            "classId": 11386592,
            "description": "",
            "geometryType": "rectangle",
            "labelerLogin": "abunoman",
            "createdAt": "2023-01-28T10:09:06.483Z",
            "updatedAt": "2023-01-28T10:09:14.157Z",
            "tags": [],
            "classTitle": "shrimp",
            "points": {
                "exterior": [
                    [
                        171.0,
                        197.0
                    ],
                    [
                        187.0,
                        239.0
                    ]
                ],
                "interior": []
            }
        },
        {
            "id": 1173192850,
            "classId": 11386592,
            "description": "",
            "geometryType": "rectangle",
            "labelerLogin": "abunoman",
            "createdAt": "2023-01-28T10:09:08.985Z",
            "updatedAt": "2023-01-28T10:09:14.157Z",
            "tags": [],
            "classTitle": "shrimp",
            "points": {
                "exterior": [
                    [
                        74.0,
                        223.0
                    ],
                    [
                        128.0,
                        239.0
                    ]
                ],
                "interior": []
            }
        },
        {
            "id": 1173192851,
            "classId": 11386592,
            "description": "",
            "geometryType": "rectangle",
            "labelerLogin": "abunoman",
            "createdAt": "2023-01-28T10:09:13.906Z",
            "updatedAt": "2023-01-28T10:09:13.906Z",
            "tags": [],
            "classTitle": "shrimp",
            "points": {
                "exterior": [
                    [
                        260.0,
                        24.0
                    ],
                    [
                        293.0,
                        228.0
                    ]
                ],
                "interior": []
            }
        }
    ],
    "size": {
        "height": 240,
        "width": 320
    }
}