{
    "tags": [],
    "description": "",
    "objects": [
        {
            "id": 1173182585,
            "classId": 11386592,
            "description": "",
            "geometryType": "rectangle",
            "labelerLogin": "masum",
            "createdAt": "2023-01-28T05:20:43.151Z",
            "updatedAt": "2023-01-28T05:21:28.295Z",
            "tags": [],
            "classTitle": "shrimp",
            "points": {
                "exterior": [
                    [
                        58.0,
                        0.0
                    ],
                    [
                        138.0,
                        152.0
                    ]
                ],
                "interior": []
            }
        },
        {
            "id": 1173182589,
            "classId": 11386592,
            "description": "",
            "geometryType": "rectangle",
            "labelerLogin": "masum",
            "createdAt": "2023-01-28T05:20:53.661Z",
            "updatedAt": "2023-01-28T05:21:28.295Z",
            "tags": [],
            "classTitle": "shrimp",
            "points": {
                "exterior": [
                    [
                        154.0,
                        181.0
                    ],
                    [
                        196.0,
                        239.0
                    ]
                ],
                "interior": []
            }
        },
        {
            "id": 1173182592,
            "classId": 11386592,
            "description": "",
            "geometryType": "rectangle",
            "labelerLogin": "masum",
            "createdAt": "2023-01-28T05:21:02.218Z",
            "updatedAt": "2023-01-28T05:21:28.295Z",
            "tags": [],
            "classTitle": "shrimp",
            "points": {
                "exterior": [
                    [
                        145.0,
                        2.0
                    ],
                    [
                        189.0,
                        126.0
                    ]
                ],
                "interior": []
            }
        },
        {
            "id": 1173182596,
            "classId": 11386592,
            "description": "",
            "geometryType": "rectangle",
            "labelerLogin": "masum",
            "createdAt": "2023-01-28T05:21:07.266Z",
            "updatedAt": "2023-01-28T05:21:28.295Z",
            "tags": [],
            "classTitle": "shrimp",
            "points": {
                "exterior": [
                    [
                        210.0,
                        0.0
                    ],
                    [
                        255.0,
                        65.0
                    ]
                ],
                "interior": []
            }
        },
        {
            "id": 1173182602,
            "classId": 11386592,
            "description": "",
            "geometryType": "rectangle",
            "labelerLogin": "masum",
            "createdAt": "2023-01-28T05:21:20.978Z",
            "updatedAt": "2023-01-28T05:21:28.295Z",
            "tags": [],
            "classTitle": "shrimp",
            "points": {
                "exterior": [
                    [
                        47.0,
                        117.0
                    ],
                    [
                        143.0,
                        237.0
                    ]
                ],
                "interior": []
            }
        },
        {
            "id": 1173182604,
            "classId": 11386592,
            "description": "",
            "geometryType": "rectangle",
            "labelerLogin": "masum",
            "createdAt": "2023-01-28T05:21:28.027Z",
            "updatedAt": "2023-01-28T05:21:28.027Z",
            "tags": [],
            "classTitle": "shrimp",
            "points": {
                "exterior": [
                    [
                        24.0,
                        120.0
                    ],
                    [
                        122.0,
                        240.0
                    ]
                ],
                "interior": []
            }
        }
    ],
    "size": {
        "height": 240,
        "width": 320
    }
}