{
    "tags": [],
    "description": "",
    "objects": [
        {
            "id": 1173185005,
            "classId": 11386592,
            "description": "",
            "geometryType": "rectangle",
            "labelerLogin": "Rakib123",
            "createdAt": "2023-01-28T06:23:33.893Z",
            "updatedAt": "2023-01-28T06:23:37.249Z",
            "tags": [],
            "classTitle": "shrimp",
            "points": {
                "exterior": [
                    [
                        228.0,
                        0.0
                    ],
                    [
                        273.0,
                        89.0
                    ]
                ],
                "interior": []
            }
        },
        {
            "id": 1173185010,
            "classId": 11386592,
            "description": "",
            "geometryType": "rectangle",
            "labelerLogin": "Rakib123",
            "createdAt": "2023-01-28T06:23:36.721Z",
            "updatedAt": "2023-01-28T06:23:36.721Z",
            "tags": [],
            "classTitle": "shrimp",
            "points": {
                "exterior": [
                    [
                        191.0,
                        0.0
                    ],
                    [
                        220.0,
                        106.0
                    ]
                ],
                "interior": []
            }
        },
        {
            "id": 1173185012,
            "classId": 11386592,
            "description": "",
            "geometryType": "rectangle",
            "labelerLogin": "Rakib123",
            "createdAt": "2023-01-28T06:23:38.956Z",
            "updatedAt": "2023-01-28T06:23:38.956Z",
            "tags": [],
            "classTitle": "shrimp",
            "points": {
                "exterior": [
                    [
                        261.0,
                        210.0
                    ],
                    [
                        291.0,
                        239.0
                    ]
                ],
                "interior": []
            }
        }
    ],
    "size": {
        "height": 240,
        "width": 320
    }
}