{
    "tags": [],
    "description": "",
    "objects": [
        {
            "id": 1173243773,
            "classId": 11386592,
            "description": "",
            "geometryType": "rectangle",
            "labelerLogin": "abunoman",
            "createdAt": "2023-01-28T12:54:40.209Z",
            "updatedAt": "2023-01-28T12:54:40.209Z",
            "tags": [],
            "classTitle": "shrimp",
            "points": {
                "exterior": [
                    [
                        207.0,
                        0.0
                    ],
                    [
                        277.0,
                        222.0
                    ]
                ],
                "interior": []
            }
        }
    ],
    "size": {
        "height": 240,
        "width": 320
    }
}